ciso8601.cpython-37m-i386-linux-gnu.so
ciso8601/py.typed
ciso8601/__init__.pyi
ciso8601_wheels-2.2.0.dist-info/LICENSE
ciso8601_wheels-2.2.0.dist-info/METADATA
ciso8601_wheels-2.2.0.dist-info/top_level.txt
ciso8601_wheels-2.2.0.dist-info/WHEEL
ciso8601_wheels-2.2.0.dist-info/RECORD
